dbqq/__init__.py
dbqq/cli/__init__.py
dbqq/cli/clean_connections.py
dbqq/cli/initialize_connections.py
dbqq/cli/run_query.py
dbqq/connectors/__init__.py
dbqq/connectors/_base.py
dbqq/connectors/_polar_connector.py
dbqq/connectors/databricks.py
dbqq/connectors/mssql.py
dbqq/connectors/oracle.py
dbqq/connectors/redshift.py
dbqq/data/__init__.py
dbqq/data/parsed/__init__.py
dbqq/data/parsed/sql.py
dbqq/security/__init__.py
dbqq/security/cli/__init__.py
dbqq/security/cli/decrypt_yaml.py
dbqq/security/cli/encrypt_yaml.py
dbqq/security/cli/write_keys.py
dbqq/security/functions/__init__.py
dbqq/security/functions/_functions.py
dbqq/security/functions/_yaml.py
dbqq/security/helpers.py
dbqq/utils.py
dbqq-1.6.1.dist-info/METADATA
dbqq-1.6.1.dist-info/WHEEL
dbqq-1.6.1.dist-info/entry_points.txt
dbqq-1.6.1.dist-info/RECORD
