Metadata-Version: 2.1
Name: dbqq
Version: 1.6.1
Summary: 
License: MIT
Author: Chris.Mamon
Author-email: chrisam1993@live.com
Requires-Python: >=3.7,<4.0
Classifier: License :: OSI Approved :: MIT License
Classifier: Programming Language :: Python :: 3
Classifier: Programming Language :: Python :: 3.7
Classifier: Programming Language :: Python :: 3.8
Classifier: Programming Language :: Python :: 3.9
Classifier: Programming Language :: Python :: 3.10
Classifier: Programming Language :: Python :: 3.11
Classifier: Programming Language :: Python :: 3.12
Classifier: Programming Language :: Python :: 3.13
Requires-Dist: arrow_odbc (>=8.0.1)
Requires-Dist: boto3 (>=1.28.2)
Requires-Dist: connectorx (>=0.3.2)
Requires-Dist: databricks-sql-connector (>=2.7.0,<3.0.0)
Requires-Dist: jinja2 (>=3.1.2,<4.0.0)
Requires-Dist: polars (>=0.18.7)
Requires-Dist: pyaml (>=23.7.0,<24.0.0)
Requires-Dist: pyarrow (>=12.0.1)
Requires-Dist: rsa (>=4.9,<5.0)
Requires-Dist: tabulate (>=0.9.0,<0.10.0)
Requires-Dist: triple-quote-clean (>=1.1.0,<2.0.0)
